README.txt
setup.py
BLhello/__init__.py
BLhello.egg-info/PKG-INFO
BLhello.egg-info/SOURCES.txt
BLhello.egg-info/dependency_links.txt
BLhello.egg-info/top_level.txt
BLhello.egg-info/zip-safe