Metadata-Version: 1.1
Name: BLhello
Version: 1.0.1
Summary: this is going to say Hello to world!
Home-page: https://github.com/joeychu1986/web_app
Author: Joey Chu
Author-email: cqtcwr@gmail.com
License: MIT
Keywords: test python package
Platform: UNKNOWN
Classifier: License :: OSI Approved :: MIT License
Classifier: Programming Language :: Python
Classifier: Intended Audience :: Developers
Classifier: Operating System :: OS Independent
